Metadata-Version: 2.4
Name: hmlr
Version: 0.1.2
Summary: Hierarchical Memory with Lattice Retrieval - AI agent memory system
Home-page: https://github.com/Sean-V-Dev/HMLR-Agentic-AI-Memory-System
Author: Sean-V-Dev
License-Expression: MIT
Project-URL: Homepage, https://github.com/Sean-V-Dev/HMLR-Agentic-AI-Memory-System
Project-URL: Repository, https://github.com/Sean-V-Dev/HMLR-Agentic-AI-Memory-System
Project-URL: Issues, https://github.com/Sean-V-Dev/HMLR-Agentic-AI-Memory-System/issues
Keywords: ai,memory,agents,rag,llm,retrieval,bridge-blocks,hierarchical-memory,openai,gpt-4.1-mini
Classifier: Development Status :: 3 - Alpha
Classifier: Intended Audience :: Developers
Classifier: Topic :: Scientific/Engineering :: Artificial Intelligence
Classifier: Topic :: Software Development :: Libraries :: Python Modules
Classifier: Programming Language :: Python :: 3
Classifier: Programming Language :: Python :: 3.10
Classifier: Programming Language :: Python :: 3.11
Classifier: Programming Language :: Python :: 3.12
Classifier: Operating System :: OS Independent
Requires-Python: >=3.10
License-File: LICENSE
Requires-Dist: openai>=1.0.0
Requires-Dist: sentence-transformers>=2.2.0
Requires-Dist: numpy>=1.24.0
Provides-Extra: langchain
Requires-Dist: langchain>=0.1.0; extra == "langchain"
Requires-Dist: langchain-openai>=0.1.0; extra == "langchain"
Provides-Extra: telemetry
Requires-Dist: arize-phoenix>=4.0.0; extra == "telemetry"
Requires-Dist: opentelemetry-api>=1.20.0; extra == "telemetry"
Requires-Dist: opentelemetry-sdk>=1.20.0; extra == "telemetry"
Provides-Extra: dev
Requires-Dist: pytest>=7.0.0; extra == "dev"
Requires-Dist: pytest-asyncio>=0.21.0; extra == "dev"
Requires-Dist: ragas>=0.4.0; extra == "dev"
Requires-Dist: langsmith>=0.2.0; extra == "dev"
Requires-Dist: datasets>=2.14.0; extra == "dev"
Requires-Dist: python-dotenv>=1.0.0; extra == "dev"
Dynamic: home-page
Dynamic: license-file
Dynamic: requires-python
